MissingValues_101883060/__init__.py
MissingValues_101883060/missingval.py
MissingValues_101883060-1.0.0.dist-info/LICENSE.txt
MissingValues_101883060-1.0.0.dist-info/METADATA
MissingValues_101883060-1.0.0.dist-info/WHEEL
MissingValues_101883060-1.0.0.dist-info/entry_points.txt
MissingValues_101883060-1.0.0.dist-info/top_level.txt
MissingValues_101883060-1.0.0.dist-info/RECORD
